PirateBayAPI/__init__.py
PirateBayAPI-1.0.1.dist-info/LICENSE
PirateBayAPI-1.0.1.dist-info/METADATA
PirateBayAPI-1.0.1.dist-info/WHEEL
PirateBayAPI-1.0.1.dist-info/top_level.txt
PirateBayAPI-1.0.1.dist-info/RECORD
