Metadata-Version: 2.1
Name: PirateBayAPI
Version: 1.0.1
Summary: A PirateBay API wrapper
Author-email: x93bd0 <x93bd0@gmail.com>
License: MIT License
Project-URL: Homepage, https://github.com/x93bd0/PirateBay.py
Classifier: Programming Language :: Python :: 3
Classifier: License :: OSI Approved :: MIT License
Classifier: Operating System :: OS Independent
Requires-Python: >=3.7
License-File: LICENSE
Requires-Dist: requests
